clusteroid/__init__.py
clusteroid/__main__.py
clusteroid/app.py
clusteroid/ceph.py
clusteroid/config.py
clusteroid/crushmap.py
clusteroid/disks.py
clusteroid/hosts.py
clusteroid/metrics.py
clusteroid/pools.py
clusteroid/services.py
clusteroid/terminal.py
clusteroid/terminal_buffer.py
clusteroid/tools.py
clusteroid/ui_tools.py
clusteroid-0.0.1.dist-info/licenses/LICENSE
clusteroid-0.0.1.dist-info/METADATA
clusteroid-0.0.1.dist-info/WHEEL
clusteroid-0.0.1.dist-info/entry_points.txt
clusteroid-0.0.1.dist-info/top_level.txt
clusteroid-0.0.1.dist-info/RECORD
