Metadata-Version: 2.4
Name: clusteroid
Version: 0.0.1
Summary: Ceph management tool.
Author-email: Predrag Mandic <predrag@nul.one>
License: BSD 3-Clause License
Classifier: Development Status :: 3 - Alpha
Classifier: Environment :: Console
Classifier: Environment :: Web Environment
Classifier: Intended Audience :: System Administrators
Classifier: License :: OSI Approved :: BSD License
Classifier: Natural Language :: English
Classifier: Operating System :: POSIX :: Linux
Classifier: Programming Language :: Python :: 3 :: Only
Requires-Python: >=3.11.2
License-File: LICENSE
Requires-Dist: textual<7,>=6.1.0
Requires-Dist: textual-dev<2,>=1.7.0
Requires-Dist: textual-serve<2,>=1.1.2
Requires-Dist: click-aliases<2,>=1.0.5
Requires-Dist: click_params<1,>=0.5.0
Requires-Dist: humanize<5,>=4.13.0
Requires-Dist: textual-terminal<1,>=0.3.0
Dynamic: license-file
